{"summary": "Provides a suite of tests that verify the functionality of various Windows toolchains, including debug, multi‑configuration, and specific Visual Studio versions, by running helper routines to execute and check applications.", "business_intent": "Validate that the Windows development toolchain is correctly installed and configured, enabling reliable builds and continuous integration.", "keywords": ["Windows", "toolchain", "testing", "debug", "multi‑configuration", "Visual Studio 2017", "Visual Studio 2022", "CI", "build verification"], "summary_hash": "81fd80fcf088", "cached_at": "2026-02-08T19:33:56+00:00"}