{"summary": "Provides lexical analysis capabilities for the UDOP language, converting raw input text into a sequence of meaningful tokens for further parsing and interpretation.", "business_intent": "Facilitates the processing of UDOP scripts by supplying a tokenizer that prepares data for compilers, interpreters, or analysis tools.", "keywords": ["tokenizer", "lexical analysis", "UDOP", "tokenization", "lexer", "parsing", "language processing"], "summary_hash": "369728e53750", "cached_at": "2026-02-09T06:37:02+00:00"}