{"summary": "Encapsulates the parameters needed to request a batch of resources from a service, such as identifiers, pagination controls, and filtering criteria.", "business_intent": "Provide a single request object that allows clients to efficiently fetch multiple items in one operation, reducing round‑trips and simplifying bulk retrieval logic.", "keywords": ["retrieve", "batch", "request", "pagination", "filter", "bulk", "API"], "summary_hash": "94e5c1df5d1b", "cached_at": "2026-02-08T07:01:53+00:00"}