{"summary": "Defines a PyTorch module that performs the Graph Isomorphism Network (GIN) convolution operation within DGL, aggregating neighbor features, applying a learnable epsilon scaling, and passing the result through a user‑specified transformation and optional activation.", "business_intent": "Enable developers to easily integrate GIN layers into graph neural network models for tasks such as node or graph classification, leveraging DGL's message‑passing framework and PyTorch's autograd.", "keywords": ["graph neural network", "GIN", "convolution", "DGL", "PyTorch", "aggregation", "epsilon scaling", "feature transformation", "activation", "message passing"], "summary_hash": "6a07e37a4647", "cached_at": "2026-02-09T00:45:28+00:00"}