{"summary": "Unit test module that validates the functionality of UNETR network building blocks, checking argument handling, script execution, and output tensor shapes for basic, PR-up, and upsampling blocks.", "business_intent": "Guarantee the correctness and robustness of UNETR components used in medical image segmentation pipelines, supporting continuous integration and reliable model deployment.", "keywords": ["UNETR", "block", "unit test", "shape validation", "script execution", "PyTorch", "MONAI", "medical imaging", "segmentation", "testing"], "summary_hash": "7f6fdc179c62", "cached_at": "2026-02-08T12:21:17+00:00"}