{"summary": "A test suite that validates the PostGIS version parsing logic, covering correct extraction of version numbers, handling of invalid or missing data, and distinguishing classic and development version formats, as well as ensuring version‑dependent functions behave as expected.", "business_intent": "Guarantee accurate detection of the installed PostGIS version to support compatibility checks and conditional functionality in GIS applications.", "keywords": ["PostGIS", "version parsing", "unit testing", "validation", "compatibility", "GIS", "software testing"], "summary_hash": "73009ee10e72", "cached_at": "2026-02-08T22:23:15+00:00"}