{"summary": "Analyzes EMR cluster configurations to verify that local disks are encrypted, ensuring data-at-rest protection within the cluster setup.", "business_intent": "Enforce security compliance by detecting unencrypted local storage in EMR clusters and prompting remediation.", "keywords": ["EMR", "cluster", "encryption", "local disk", "configuration", "security", "compliance", "data protection", "AWS", "resource scanning"], "summary_hash": "88478c54f70b", "cached_at": "2026-02-08T17:54:27+00:00"}