{"summary": "Provides a sanity test that scans the project's bundled third‑party libraries, reads their version metadata, and verifies they are not older than the latest applicable upstream releases.", "business_intent": "Helps maintain the security, stability, and compatibility of the software by automatically detecting outdated bundled dependencies so they can be updated in sync with upstream releases.", "keywords": ["bundled libraries", "version checking", "upstream sync", "dependency validation", "sanity test", "code smell detection", "package version comparison", "metadata parsing", "security compliance"], "summary_hash": "20baa7c14a01", "cached_at": "2026-02-08T18:00:50+00:00"}