{"summary": "Provides a Kedro runner that executes pipeline nodes in parallel groups derived from a topological sort, coordinating worker processes and handling dataset constraints.", "business_intent": "Accelerates data engineering workflows by leveraging multi‑process execution to reduce pipeline run times while preserving data integrity for single‑process datasets.", "keywords": ["parallel execution", "pipeline orchestration", "topological sorting", "process pool", "in‑memory dataset sharing", "Kedro", "data engineering", "resource management"], "summary_hash": "5d453abb7d9d", "cached_at": "2026-02-09T10:16:41+00:00"}