{"summary": "The module defines simple Django model classes and a comprehensive set of unit tests that exercise the ORM's defer and only query modifiers, covering field deferral across model inheritance, proxy models, related object loading, values queries, and object persistence operations.", "business_intent": "Validate and safeguard Django's field deferral behavior, ensuring that deferred fields work correctly in various model configurations and that future changes do not introduce regressions.", "keywords": ["Django", "ORM", "defer", "only", "field deferral", "proxy model", "model inheritance", "select_related", "values query", "unit tests", "test suite", "database queries", "model saving", "refresh_from_db"], "summary_hash": "3f88ad8a6b8a", "cached_at": "2026-02-09T01:37:21+00:00"}