{"summary": "Implements a positional convolutional embedding layer for wav2vec 2.0 models using Flax, generating position-aware representations of audio feature sequences.", "business_intent": "Provides the core component that injects positional information into speech representations, enabling more accurate speech recognition and other audio downstream applications.", "keywords": ["Flax", "JAX", "wav2vec 2.0", "positional embedding", "convolution", "audio", "speech processing", "neural network", "feature extraction", "sequence modeling"], "summary_hash": "f8845cbe2de0", "cached_at": "2026-02-09T10:22:26+00:00"}