{"summary": "A utility class that prepares configurations and synthetic data, instantiates various GPT‑J model variants, and runs forward and backward checks to validate their behavior under different conditions such as attention masks, past key values, large inputs, and language‑model heads.", "business_intent": "Automate verification of GPT‑J model implementations to guarantee functional correctness, performance stability, and integration readiness within machine‑learning pipelines.", "keywords": ["GPT-J", "model testing", "configuration generation", "synthetic inputs", "forward pass validation", "backward pass validation", "attention mask handling", "past key values", "large input support", "language modeling head", "pipeline integration"], "summary_hash": "6687ebb15aec", "cached_at": "2026-02-09T04:48:39+00:00"}