{"summary": "Encapsulates a GC100 hardware switch/relay, offering access to its name, current on/off state, methods to change the state, and a way to refresh its status.", "business_intent": "Allow software to programmatically control and monitor a GC100-connected relay for automation tasks, such as turning devices on or off and keeping the state in sync with the hardware.", "keywords": ["GC100", "switch", "relay", "state", "on/off", "control", "monitor", "update", "automation", "hardware"], "summary_hash": "388137384ca6", "cached_at": "2026-02-09T04:59:33+00:00"}