{"summary": "A test suite that validates the generation and content of various email notifications such as review, comment, internal error, and subscription messages.", "business_intent": "Automatically verify that email notifications are correctly created and dispatched for different application events, ensuring reliability and preventing regressions.", "keywords": ["email", "notification", "unit test", "review", "comment", "internal error", "subscription", "test suite", "setup", "validation"], "summary_hash": "f51c0a8a7d8d", "cached_at": "2026-02-08T14:35:54+00:00"}