{"summary": "Integration test suite that validates Automatic Mixed Precision (AMP) functionality within Lightning Fabric, using a helper module to manage mixed‑precision initialization and forward casting, and providing test cases for AMP behavior and optimizer parity.", "business_intent": "Ensure that AMP training works correctly and efficiently in the framework, giving developers confidence that mixed‑precision models and optimizers behave as expected in production pipelines.", "keywords": ["automatic mixed precision", "AMP", "Lightning Fabric", "integration test", "mixed precision module", "optimizer parity", "fused optimizer", "torch", "pytest"], "summary_hash": "22c59cbd5b15", "cached_at": "2026-02-08T08:47:35+00:00"}