{"summary": "Encapsulates a Vision Transformer‑based neural network that performs image matting, extracting foreground alpha mattes from input images.", "business_intent": "Enable automated background removal and high‑quality foreground extraction for photo editing, e‑commerce, AR, and other visual content workflows.", "keywords": ["image matting", "vision transformer", "deep learning", "foreground extraction", "background removal", "computer vision", "neural network", "AI model", "PyTorch"], "summary_hash": "30e178a9b7a3", "cached_at": "2026-02-09T10:32:28+00:00"}