{"summary": "Provides a complete mock implementation of the AWS Route53 Resolver service for the Moto testing framework, including data models for resolver endpoints and rules, validation utilities, custom exceptions, and HTTP response handling that maps API calls to backend operations.", "business_intent": "Allows developers to write and run unit or integration tests that interact with Route53 Resolver APIs without contacting the real AWS service, ensuring fast, reliable, and cost‑free testing of DNS resolver configurations.", "keywords": ["mock", "AWS", "Route53 Resolver", "DNS", "endpoint", "rule", "tagging", "validation", "pagination", "exception handling", "backend", "responses", "testing"], "summary_hash": "9404369d6848", "cached_at": "2026-02-09T10:54:25+00:00"}