{"summary": "A callable wrapper that caches the result of a supplied factory function and automatically recomputes it when a configured time-to-live expires.", "business_intent": "Reduce the cost of repeatedly invoking expensive or time-sensitive operations by providing a time-based cache that refreshes itself without manual intervention.", "keywords": ["caching", "auto-refresh", "expiration", "factory function", "time-based invalidation", "memoization", "lazy evaluation", "callable wrapper"], "summary_hash": "2da7f8f0fcf8", "cached_at": "2026-02-08T05:05:14+00:00"}