{"summary": "Defines the Qt-based graphical interface for browsing and interacting with Web Map Service (WMS) capabilities, constructing the widget hierarchy and supporting UI text translation.", "business_intent": "Allow users to explore, view, and select layers and services offered by a WMS server, facilitating integration of remote map data into the application.", "keywords": ["WMS", "capabilities", "browser", "UI", "Qt", "PyQt5", "widget", "translation", "GIS", "map service"], "summary_hash": "25756616ed01", "cached_at": "2026-02-08T08:53:33+00:00"}