{"summary": "A set of shared utility modules that supply common helper functions for the Ansible collection's plugins, enabling reusable code across the collection's modules.", "business_intent": "To streamline development and maintenance of Ansible plugins by providing a centralized library of reusable utilities, reducing duplication and ensuring consistent behavior across the collection.", "keywords": ["ansible", "collection", "module_utils", "helper functions", "shared utilities", "plugin development", "reusability", "code base"], "summary_hash": "0c9cfc79d870", "cached_at": "2026-02-08T18:35:53+00:00"}