{"summary": "Provides a unittest suite that executes a Checkov Terraform security check to confirm that Amazon MSK cluster nodes are configured as private endpoints, verifying the check's behavior against sample Terraform configurations.", "business_intent": "Guarantee that infrastructure-as-code for Amazon MSK does not expose cluster nodes publicly, supporting security compliance and reducing the risk of unauthorized access.", "keywords": ["Terraform", "Checkov", "unit testing", "Amazon MSK", "private endpoints", "security compliance", "infrastructure as code", "cloud security", "resource validation"], "summary_hash": "a6f9755fc6f3", "cached_at": "2026-02-08T21:51:42+00:00"}