{"summary": "Provides a mapping-like view of edge attributes for a specific edge type in a heterogeneous graph, allowing read, write, delete, iteration and size queries, as well as helper operations such as key/value enumeration and transposition.", "business_intent": "Enable users to conveniently access and manipulate edge data associated with a particular edge type without copying, supporting typical dictionary operations and specialized transformations.", "keywords": ["heterogeneous graph", "edge data view", "mapping interface", "attribute access", "iteration", "keys", "values", "transpose"], "summary_hash": "92bd8bcf049b", "cached_at": "2026-02-08T23:34:35+00:00"}