{"summary": "Provides the core socket‑IO handling for the MSColab collaborative environment, coordinating real‑time events such as file updates, permission changes, chat messages and user connection management, while applying permission checks and tracking active collaborators.", "business_intent": "Facilitates live, multi‑user collaboration on flight‑planning data, ensuring synchronized state, secure access control and instant communication among participants.", "keywords": ["socket.io", "real-time", "collaboration", "file synchronization", "permission management", "chat", "Flask", "MSColab", "event handling"], "summary_hash": "7e64d750bde4", "cached_at": "2026-02-08T08:49:05+00:00"}