{"summary": "A foundational class for Flax (JAX) models that encapsulates common functionality such as configuration handling, weight initialization, loading and saving pretrained parameters, and device placement.", "business_intent": "Enable developers to quickly build, fine‑tune, and deploy Flax‑based machine learning models by providing a standardized interface for managing model configurations and pretrained weights.", "keywords": ["Flax", "JAX", "pretrained model", "configuration", "weight loading", "serialization", "base class", "machine learning", "model initialization"], "summary_hash": "f52c746fb39a", "cached_at": "2026-02-09T06:37:44+00:00"}