{"summary": "A comprehensive test suite that validates the correctness and compatibility of various linear algebra operations—such as eigenvalue decompositions, LU/QR factorizations, SVD, and triangular solves—across multiple hardware backends (CPU, GPU, TPU) and library implementations.", "business_intent": "To guarantee numerical accuracy and cross‑platform consistency of linear algebra kernels within a machine learning framework, enabling reliable deployment on diverse hardware.", "keywords": ["compatibility testing", "linear algebra", "eigenvalue decomposition", "LU decomposition", "QR factorization", "SVD", "triangular solve", "CPU", "GPU", "TPU", "stablehlo", "custom call verification", "numerical accuracy"], "summary_hash": "3b77e590ca76", "cached_at": "2026-02-09T11:21:11+00:00"}