{"summary": "A Flax-based implementation of the small BlenderBot architecture that encapsulates the model's parameters, configuration, and forward computation for conversational language generation.", "business_intent": "Provide developers and researchers with a lightweight, efficient chatbot model that can be trained or deployed using JAX/Flax, reducing computational resources while delivering conversational AI capabilities.", "keywords": ["Flax", "BlenderBot", "small model", "conversational AI", "chatbot", "JAX", "transformer", "NLP", "lightweight", "language generation"], "summary_hash": "8bf5d5b24d9d", "cached_at": "2026-02-09T06:40:14+00:00"}