{"summary": "Provides functionality to verify and enforce that an application service is configured to accept only HTTPS traffic, ensuring secure communication for the hosted web application.", "business_intent": "Guarantee that web services are protected against unencrypted HTTP access, supporting compliance and security policies for cloud-hosted applications.", "keywords": ["App Service", "HTTPS only", "security", "configuration enforcement", "Azure", "compliance", "encrypted traffic", "inspection key"], "summary_hash": "0357cc633855", "cached_at": "2026-02-08T17:28:40+00:00"}