{"summary": "Evaluates password reuse settings within a resource's configuration, exposing the relevant configuration key and the expected compliance value, and scans the configuration to verify adherence.", "business_intent": "Enforce security compliance by detecting and flagging password policies that permit reuse, ensuring that resources follow strict password reuse restrictions.", "keywords": ["password", "policy", "reuse", "configuration", "compliance", "security", "scanner", "expected value", "inspection"], "summary_hash": "2d792c765835", "cached_at": "2026-02-08T17:54:36+00:00"}