{"summary": "Encapsulates the definition of a command's input and output parameters, providing methods to incrementally add, combine, and manage these I/O specifications based on configuration.", "business_intent": "Enables dynamic construction and merging of command I/O definitions to support flexible command configuration and execution.", "keywords": ["command", "input", "output", "definition", "configuration", "merge", "helper", "IO", "specification"], "summary_hash": "c1e5686ab089", "cached_at": "2026-02-08T15:45:25+00:00"}