{"summary": "Provides the command‑line interface for creating and registering Prefect flow deployments, handling configuration files, Docker image builds, schedules, triggers, and remote storage integration.", "business_intent": "Allow users to automate the setup and registration of workflow deployments from the terminal, simplifying the process of configuring runtime environments, scheduling, and deployment metadata for Prefect projects.", "keywords": ["deployment", "CLI", "Prefect", "flow", "schedule", "Docker", "trigger", "configuration", "registration", "remote storage", "yaml"], "summary_hash": "e8dad7a11b28", "cached_at": "2026-02-08T13:25:32+00:00"}