{"summary": "A test suite that validates the behavior of the fail2ban monitoring sensor, checking ban activation, handling of multiple jails, multiple bans, and unbanning operations.", "business_intent": "Guarantee accurate detection and management of fail2ban bans within the monitoring system to maintain security posture and reliable alerting.", "keywords": ["fail2ban", "sensor", "unit testing", "ban detection", "multiple jails", "unban", "setup", "teardown"], "summary_hash": "3d16139e08d9", "cached_at": "2026-02-09T05:29:29+00:00"}