{"summary": "Provides core utilities for applying dropout‑style image augmentations, including random region erasure, channel removal, and inpainting, while maintaining consistency of related annotations such as masks, bounding boxes, and keypoints.", "business_intent": "Support data‑augmentation pipelines that introduce occlusions or missing information to train more robust computer‑vision models.", "keywords": ["image augmentation", "dropout", "random erasing", "cutout", "channel dropout", "inpainting", "hole filling", "annotation handling", "bounding boxes", "keypoints", "computer vision", "data robustness"], "summary_hash": "137b40a9c5d4", "cached_at": "2026-02-08T15:28:46+00:00"}