{"summary": "Encapsulates metadata for a Python array API namespace, providing access to its capabilities, default device, supported data types, and available devices.", "business_intent": "Enables frameworks and applications to query an array library's features at runtime, facilitating backend selection, compatibility checks, and device‑agnostic computation.", "keywords": ["array API", "metadata", "capabilities", "default device", "data types", "namespace", "backend discovery", "compatibility", "introspection"], "summary_hash": "ef0c8ef01734", "cached_at": "2026-02-09T11:36:01+00:00"}