{"summary": "Encapsulates configuration data for a raster transformer in a mock environment and offers helper methods to instantiate local transformers, prepare prediction settings, load and save bundled files, serialize to protocol buffers, and adjust the configuration for specific commands.", "business_intent": "Facilitates testing and lightweight deployment of raster transformation pipelines by providing a configurable, serializable mock transformer setup that can be quickly created, persisted, and adapted for prediction tasks.", "keywords": ["raster", "transformer", "configuration", "mock", "helper", "serialization", "prediction", "bundle", "proto", "factory", "command"], "summary_hash": "7ee27901fef2", "cached_at": "2026-02-08T15:37:30+00:00"}