{"summary": "Implements a parser that processes Mojo source code, utilizing the Mojo lexer to tokenize input and constructing an abstract syntax tree (AST) representation.", "business_intent": "Enable the backend of the crosstl system to understand and transform Mojo programs by providing syntactic analysis and AST generation for further compilation or analysis steps.", "keywords": ["Mojo", "parser", "lexer", "AST", "syntax analysis", "compiler backend", "source code parsing"], "summary_hash": "c4429e4b199f", "cached_at": "2026-02-08T05:37:05+00:00"}