{"summary": "Provides a utility to clean up experiment-related data within a DVC repository, removing temporary files and metadata associated with experiments.", "business_intent": "Enable users to maintain a tidy repository by deleting stale or unnecessary experiment artifacts, improving storage efficiency and repository hygiene.", "keywords": ["clean", "experiments", "DVC", "repository", "utility", "metadata", "temporary files", "cleanup"], "summary_hash": "75ecb5e344fe", "cached_at": "2026-02-09T09:27:30+00:00"}