{"summary": "The file defines a custom enumeration class that allows multiple members to share identical values and stores a designated default member in a .default attribute.", "business_intent": "Facilitate the use of enums with duplicate values while providing a clear default option for configuration, state management, or fallback scenarios.", "keywords": ["enum", "duplicate values", "default member", "fallback", "configuration", "state management", "custom constructor"], "summary_hash": "0784027c7347", "cached_at": "2026-02-08T13:03:54+00:00"}