{"summary": "Manages the lifecycle and state of a background daemon, providing operations to initiate, halt, and query its condition while handling online/offline state transitions.", "business_intent": "Allow applications to programmatically control a supporting daemon, ensuring reliable start, stop, and status monitoring as part of the system's operational workflow.", "keywords": ["daemon", "service lifecycle", "process control", "status monitoring", "state management", "online/offline handling", "automation"], "summary_hash": "fc9e18279b7e", "cached_at": "2026-02-08T19:00:37+00:00"}