{"summary": "Defines selectable execution modes for the HoVerNet neural network, distinguishing a performance‑optimized fast variant from the reference original implementation.", "business_intent": "Enables developers to configure the HoVerNet model for either higher inference speed or exact replication of the published algorithm, supporting flexible deployment in medical image segmentation pipelines.", "keywords": ["HoVerNet", "mode selection", "fast implementation", "original implementation", "enumeration", "model configuration", "performance optimization", "segmentation"], "summary_hash": "bfc8fed79f09", "cached_at": "2026-02-08T11:08:54+00:00"}