{"summary": "A test suite that validates the implementation of the standard Cauchy distribution, checking generated values, finiteness, and goodness‑of‑fit using a Kolmogorov‑Smirnov assessment.", "business_intent": "Provide confidence that statistical components handling the Cauchy distribution behave correctly, supporting analytics, risk assessment, and scientific computing applications.", "keywords": ["Cauchy distribution", "standard Cauchy", "unit testing", "statistical validation", "Kolmogorov‑Smirnov test", "finite values", "random sampling"], "summary_hash": "4085d0d3dab9", "cached_at": "2026-02-08T19:56:27+00:00"}