{"summary": "Encapsulates a spatial grid of cells, interpreting integer codes to designate each cell as active, inactive, or a constant‑head location for groundwater flow simulations.", "business_intent": "Provides a clear, programmatic representation of model boundary conditions to facilitate setup and execution of groundwater flow models such as MODFLOW.", "keywords": ["boundary conditions", "groundwater modeling", "active cells", "inactive cells", "constant head", "IBOUND", "DataArray", "spatial grid", "simulation", "MODFLOW", "cell classification"], "summary_hash": "3a798bb6800e", "cached_at": "2026-02-08T06:28:02+00:00"}