{"summary": "Provides helper methods for unit tests that verify the calibration builder's calculations, such as stretch duration, stretch width, and various play parameters.", "business_intent": "Validate the correctness of calibration computations and ensure reliable behavior of the calibration builder during automated testing.", "keywords": ["calibration", "testing", "stretch duration", "stretch width", "play parameters", "helper functions", "validation"], "summary_hash": "e69d8af8d2d4", "cached_at": "2026-02-08T12:24:39+00:00"}