{"summary": "Test suite that verifies the behavior of a distributed data sampler, including its interaction with cached datasets and handling of both evenly and unevenly divided data partitions, as well as scenarios where the dataset size is smaller than the number of partitions.", "business_intent": "Validate that distributed sampling works correctly for multi‑process training pipelines, ensuring balanced and deterministic data loading across workers.", "keywords": ["distributed sampler", "cache dataset", "data loader", "partitioning", "unit test", "MONAI", "PyTorch", "multiprocessing", "dataset size", "even split", "uneven split"], "summary_hash": "95b20968c3f6", "cached_at": "2026-02-08T12:27:01+00:00"}