{"summary": "Provides a Terraform static analysis rule that validates AWS CodeBuild project resources have logging configured, ensuring that build output is captured via CloudWatch Logs or S3.", "business_intent": "Enable organizations to enforce compliance and security best practices by guaranteeing that CodeBuild build logs are retained for auditability, troubleshooting, and incident response.", "keywords": ["AWS", "CodeBuild", "logging", "Terraform", "static analysis", "compliance", "security", "CloudWatch", "S3", "CI/CD"], "summary_hash": "ba600972c7ec", "cached_at": "2026-02-08T20:41:06+00:00"}