{"summary": "A test suite that validates the behavior of a file‑filtering utility under various configurations, such as default inclusion, directory exclusion, file‑type selection, comment handling, and override precedence.", "business_intent": "Guarantee that the file‑filter component works correctly in production scenarios like build pipelines, deployment scripts, or content management systems, reducing bugs related to incorrect file selection.", "keywords": ["unit testing", "file filtering", "directory exclusion", "filetype selection", "override precedence", "comment parsing", "software quality", "test suite", "build automation", "deployment"], "summary_hash": "272248d7be17", "cached_at": "2026-02-08T11:53:24+00:00"}