{"summary": "A collection of custom Django template tag libraries that extend the templating system with utilities for string operations, dictionary access, form field rendering with validation errors, formset detection, URL construction with namespaces and public domains, organization data retrieval, and in‑template debugging.", "business_intent": "Enable developers to write cleaner, more maintainable templates by providing reusable tags and filters that handle common presentation logic, simplify debugging, and ensure consistent URL generation across the application.", "keywords": ["Django", "template tags", "custom filters", "string manipulation", "form rendering", "validation errors", "formset detection", "URL generation", "debugging", "organization data", "template utilities"], "summary_hash": "29c40db7fcbc", "cached_at": "2026-02-08T17:39:09+00:00"}