{"summary": "Implements a raster transformer that rescales non‑uint8 raster data to 8‑bit unsigned integer arrays using per‑band statistical metrics, ensuring the transformed imagery retains relative contrast and distribution.", "business_intent": "Standardize raster inputs for machine‑learning and visualization pipelines by converting diverse numeric pixel types to a common 0‑255 range, reducing storage size and simplifying model ingestion.", "keywords": ["raster", "transformer", "statistics", "scaling", "uint8 conversion", "image preprocessing", "data normalization", "pixel value rescaling"], "summary_hash": "82086f244ed9", "cached_at": "2026-02-08T15:59:40+00:00"}