{"summary": "Encapsulates device-specific tensor layout metadata, offering standard object behavior and utilities to translate the layout to XLA format, verify compatibility with abstract values, and instantiate from PJRT layout descriptors.", "business_intent": "Facilitates consistent handling and conversion of tensor memory layouts across different runtime backends, ensuring that device-local data structures are compatible and efficiently executable.", "keywords": ["device layout", "tensor metadata", "XLA conversion", "PJRT integration", "compatibility check", "abstract value", "memory ordering", "runtime translation"], "summary_hash": "56576db3a54a", "cached_at": "2026-02-09T11:30:31+00:00"}