{"summary": "A collection of unit tests that validate the Remote integration in Home Assistant, checking state reporting, command transmission, service handling, and power toggling functionality.", "business_intent": "Guarantee that the Remote component behaves correctly within the Home Assistant platform, providing confidence that users can control remote devices reliably through services and state changes.", "keywords": ["remote", "Home Assistant", "unit tests", "state reporting", "command sending", "service interaction", "power toggle", "integration testing"], "summary_hash": "f452ef657d9e", "cached_at": "2026-02-09T07:08:44+00:00"}