{"summary": "Encapsulates a transformer‑based neural network for processing three‑dimensional data, handling model initialization and loading from configuration files or pretrained checkpoints.", "business_intent": "Provide developers with a plug‑and‑play 3D transformer model that can be quickly integrated into applications for 3D shape generation, reconstruction, or analysis, reducing the effort required to build and train such architectures from scratch.", "keywords": ["transformer", "3D", "neural network", "model loading", "pretrained", "configuration", "deep learning", "geometry", "shape generation", "reconstruction"], "summary_hash": "74a13ba6640e", "cached_at": "2026-02-09T03:41:46+00:00"}