{"summary": "A test suite that verifies batch generation functionality of a Marian translation model handling English source text and multiple Romance language targets.", "business_intent": "Ensure the translation system correctly processes and generates batches for multilingual target languages, supporting quality and performance checks for English-to-Romance translations.", "keywords": ["testing", "multilingual", "batch generation", "translation", "English", "Romance languages", "Marian model", "unit test", "validation", "helper"], "summary_hash": "1b32e2f2e0af", "cached_at": "2026-02-09T05:24:24+00:00"}