{"summary": "This module contains unit tests that validate the behavior of the FactoredMatrix constructor, checking handling of leading dimensions, broadcasting rules, and shape mismatches during initialization.", "business_intent": "Guarantee reliable creation of FactoredMatrix objects for transformer model components by catching dimension and shape errors early in the development cycle.", "keywords": ["FactoredMatrix", "constructor", "unit test", "dimension validation", "broadcasting", "shape mismatch", "PyTorch", "pytest"], "summary_hash": "6fbbed701e20", "cached_at": "2026-02-08T13:22:48+00:00"}