{"summary": "Provides unit tests for the MoldIndicator sensor, covering initialization, calculation logic, handling of invalid humidity values, and detection of sensor changes.", "business_intent": "Ensures the mold detection sensor delivers accurate and reliable measurements for environmental monitoring applications, supporting quality assurance and compliance.", "keywords": ["unit testing", "sensor validation", "mold indicator", "humidity handling", "calculation verification", "setup teardown", "quality assurance", "environmental monitoring"], "summary_hash": "9d8fffc79c7b", "cached_at": "2026-02-09T05:27:13+00:00"}