{"summary": "Provides convenient methods to extract and manipulate cross‑sectional slices of a UxDataArray along fixed latitude or longitude lines, supporting single‑value slices, interval ranges, and generic cross‑section analysis.", "business_intent": "Enable scientists and engineers to quickly retrieve and analyze horizontal or vertical slices of multidimensional geospatial datasets for visualization, statistical evaluation, or model validation.", "keywords": ["cross-section", "latitude slice", "longitude slice", "interval extraction", "geospatial data", "UxDataArray", "data accessor", "slice analysis", "scientific computing"], "summary_hash": "a1e8872e8618", "cached_at": "2026-02-08T14:22:32+00:00"}