{"summary": "Defines an extensible contract for handling API tokens, covering schema creation, encoding/decoding, preprocessing, post‑processing, and augmentation with extra fields.", "business_intent": "Provide a flexible foundation for authentication/authorization systems to generate, validate, and customize API tokens while allowing future extensions.", "keywords": ["api token", "encoding", "decoding", "schema", "preprocessing", "postprocessing", "extra fields", "extensibility", "authentication", "authorization"], "summary_hash": "f4880b29cf46", "cached_at": "2026-02-08T18:52:08+00:00"}