{"summary": "The module contains a comprehensive set of unit tests for the MetaTensor class, exercising its creation, metadata tracking, arithmetic and indexing operations, device placement, transformation pipelines, serialization/deserialization, and interaction with MONAI data loading utilities and multiprocessing.", "business_intent": "Validate the correctness and robustness of MetaTensor to guarantee reliable handling of image data and associated metadata in medical imaging workflows, supporting downstream model development and deployment.", "keywords": ["MetaTensor", "unit testing", "metadata management", "tensor operations", "device handling", "data transforms", "serialization", "data loading", "MONAI", "PyTorch", "multiprocessing"], "summary_hash": "e2e263ebb582", "cached_at": "2026-02-08T12:31:44+00:00"}