{"summary": "Provides core utilities for configuring a Kedro project, encapsulating settings with validation rules, managing logging configuration, and exposing pipelines through a lazy, read‑only container.", "business_intent": "Enable reliable project setup by validating configuration values, initializing logging, and offering on‑demand access to pipeline definitions, thereby simplifying project initialization and ensuring consistent behavior.", "keywords": ["kedro", "project configuration", "settings management", "validation", "dynaconf", "logging", "pipeline discovery", "lazy loading", "catalog protocol", "subclass validation"], "summary_hash": "364212f15064", "cached_at": "2026-02-09T10:18:27+00:00"}