{"summary": "Implements Home Assistant's fan integration, defining a generic fan entity model, supported features, service schemas, and a suite of platform-specific implementations for a wide range of fan hardware, enabling unified control of power, speed, direction, oscillation, and device‑specific functions.", "business_intent": "Provides a centralized, extensible framework for users to monitor and control fan devices from many manufacturers within Home Assistant, simplifying smart‑home fan management and supporting automation across diverse protocols and brands.", "keywords": ["Home Assistant", "fan integration", "device control", "speed", "oscillation", "power", "Zigbee", "Z-Wave", "MQTT", "Dyson", "Xiaomi", "template", "automation"], "summary_hash": "bb3191c04cfc", "cached_at": "2026-02-09T07:12:05+00:00"}