{"summary": "Provides CDK stack definitions used in integration tests to validate the public accessibility configuration of Amazon Redshift clusters, including both a compliant (publicly accessible) and a non‑compliant scenario.", "business_intent": "To automatically test and enforce compliance rules regarding whether Redshift clusters are allowed to be publicly accessible, ensuring infrastructure code meets security policies.", "keywords": ["AWS CDK", "Amazon Redshift", "publicly accessible", "compliance testing", "integration test", "IAM role", "parameter group", "infrastructure as code", "Python"], "summary_hash": "3a1476a3467f", "cached_at": "2026-02-08T22:08:38+00:00"}