{"summary": "A Dask-compatible collection that integrates with the Dask task graph system, providing lazy evaluation and convenient helpers for triggering computation, caching results, and visualizing the task graph.", "business_intent": "Allow users to handle large or distributed data using Dask's parallel execution model, offering simple interfaces to compute results, persist intermediate data, and inspect the computation workflow.", "keywords": ["dask", "lazy evaluation", "task graph", "compute", "persist", "visualize", "parallel processing", "distributed data", "collection"], "summary_hash": "a0af62e1a2fd", "cached_at": "2026-02-08T23:11:16+00:00"}