{"summary": "Mixin that equips a model with a name attribute with natural ordering and a class‑level lookup helper, enabling objects to be compared by their name and retrieved via a simple name‑based query.", "business_intent": "Facilitate easy searching and sorting of records by their textual name, improving code readability and reducing boilerplate for name‑based operations.", "keywords": ["name", "search", "sorting", "lookup", "mixin", "ordering", "ORM", "query", "filter"], "summary_hash": "2e1c88e48d88", "cached_at": "2026-02-08T18:53:45+00:00"}