{"summary": "Represents a vector construction expression within an abstract syntax tree, encapsulating the data needed to model a vector literal in source code.", "business_intent": "Enables the parser and later compilation or interpretation stages to recognize, manipulate, and generate code for vector literals, supporting language features that involve vector creation.", "keywords": ["vector", "constructor", "AST node", "syntax tree", "literal", "expression", "compiler", "parser"], "summary_hash": "102915e5c691", "cached_at": "2026-02-08T05:31:51+00:00"}