{"summary": "Provides unit tests that validate matrix multiplication functionality using both a GPU-accelerated library and the standard operator overload.", "business_intent": "Ensures reliable and correct matrix multiplication across different implementations, supporting quality assurance and performance verification for computational workloads.", "keywords": ["matrix multiplication", "unit test", "GPU", "cupy", "operator overload", "validation", "performance"], "summary_hash": "2ca887f6632e", "cached_at": "2026-02-08T19:40:23+00:00"}