{"summary": "A unit test module that verifies the Terraform graph builder's capabilities, including standard graph construction, integration with additional modules, proper handling of Terraform modules and variables, and resource cleanup after execution.", "business_intent": "To ensure the reliability and correctness of the infrastructure-as-code analysis tool by automatically testing the graph generation logic for Terraform configurations, thereby preventing regressions and supporting future enhancements.", "keywords": ["Terraform", "graph builder", "unit tests", "runner", "modules", "variables", "cleanup", "networkx", "rustworkx", "parameterized", "unittest"], "summary_hash": "59a6590b1344", "cached_at": "2026-02-08T21:18:36+00:00"}