{"summary": "Encapsulates all configurable parameters that control the behavior of the model training loop, such as iteration counts, data handling, optimization settings, and runtime options.", "business_intent": "Enable users to specify and manage training hyperparameters in a structured way to facilitate reproducible and customizable model training processes.", "keywords": ["training loop", "hyperparameters", "configuration", "epochs", "batch size", "learning rate", "optimizer", "scheduler", "early stopping", "model training"], "summary_hash": "42c9be4e0548", "cached_at": "2026-02-09T06:07:54+00:00"}