{"summary": "A neural network layer that integrates Feature-wise Linear Modulation (FiLM) into graph message passing, transforming node features within a GNN architecture.", "business_intent": "Provide a flexible, conditionally modulated graph representation component for tasks such as node classification, link prediction, and graph-level regression.", "keywords": ["graph neural network", "FiLM", "layer", "message passing", "node features", "feature modulation", "deep learning"], "summary_hash": "b76ff26b3948", "cached_at": "2026-02-08T23:18:00+00:00"}