{"summary": "Provides static mock data and a response helper for EC2 availability zones and regions, exposing formatted information that mimics AWS DescribeRegions and DescribeAvailabilityZones API responses.", "business_intent": "Enable developers to test code that interacts with EC2 region and zone queries without accessing real AWS services by supplying realistic mock responses.", "keywords": ["EC2", "availability zones", "regions", "mock responses", "testing", "Moto", "DescribeRegions", "DescribeAvailabilityZones", "AWS simulation"], "summary_hash": "921914c4596c", "cached_at": "2026-02-09T10:01:50+00:00"}