{"summary": "Manages the CILogon OpenID Connect login workflow, constructing the authorization request and handling the user redirection to the identity provider.", "business_intent": "Provide federated authentication for applications by leveraging CILogon's OIDC service to securely log in users.", "keywords": ["authentication", "OpenID Connect", "CILogon", "federated login", "authorization redirect", "identity provider", "security", "login flow"], "summary_hash": "f4bfb20bd8d4", "cached_at": "2026-02-09T09:45:52+00:00"}