{"summary": "Implements a SeamlessM4T based model that converts audio inputs into textual transcriptions, managing encoder and decoder components, weight sharing, caching, and generation of output sequences.", "business_intent": "Enable applications to perform accurate and efficient speech transcription, supporting features such as real‑time captioning, voice command processing, and content indexing.", "keywords": ["speech transcription", "audio encoding", "text decoding", "generation", "model inference", "weight tying", "cache handling", "embeddings", "SeamlessM4T", "speech-to-text"], "summary_hash": "f4adf4c0884a", "cached_at": "2026-02-09T10:53:12+00:00"}