{"summary": "Test suite that verifies the correctness and robustness of the string-to-sharding-rule parser by checking handling of factor definitions, ellipsis placement, bracket balance, scalar operands, and invalid characters.", "business_intent": "Guarantee reliable parsing of sharding rule specifications for distributed tensor operations, preventing malformed rules from causing runtime errors.", "keywords": ["sharding rule", "parser", "validation", "ellipsis", "brackets", "factor", "scalar operand", "unit tests", "error handling", "string conversion"], "summary_hash": "22ff7de662cc", "cached_at": "2026-02-09T11:11:22+00:00"}