{"summary": "Implements a convolution layer that aggregates point features using PointNet-style operations, providing forward computation and optional grouping of all points.", "business_intent": "Enable neural networks to process unordered point cloud data by summarizing local neighborhoods into higher-level representations for tasks such as 3D object classification or segmentation.", "keywords": ["point cloud", "feature aggregation", "PointNet", "convolution", "deep learning", "grouping", "neural network"], "summary_hash": "d11b202ff145", "cached_at": "2026-02-08T23:22:13+00:00"}